KegLogin-0.5.4.dist-info/DESCRIPTION.rst
KegLogin-0.5.4.dist-info/METADATA
KegLogin-0.5.4.dist-info/RECORD
KegLogin-0.5.4.dist-info/WHEEL
KegLogin-0.5.4.dist-info/metadata.json
KegLogin-0.5.4.dist-info/top_level.txt
keg_login/__init__.py
keg_login/ext.py
keg_login/forms.py
keg_login/lib.py
keg_login/middleware.py
keg_login/tokens.py
keg_login/version.py
keg_login/views.py
keg_login/templates/keg-login/_macros.html
keg_login/templates/keg-login/base.html
keg_login/templates/keg-login/change-password.html
keg_login/templates/keg-login/forgot-password.html
keg_login/templates/keg-login/keg-login-base.html
keg_login/templates/keg-login/lock.html
keg_login/templates/keg-login/login.html
keg_login/templates/keg-login/macros.html
keg_login/templates/keg-login/reset-password.html
keg_login/tests/__init__.py
keg_login/tests/test_ext.py
keg_login/tests/test_forms.py
keg_login/tests/test_middleware.py
keg_login/tests/test_tokens.py
keg_login/tests/test_views.py
keg_login/tests/test_templates/keg-login/forgot-password.html
keg_login/tests/test_templates/keg-login/test-include.html
