Metadata-Version: 2.0
Name: KegLogin
Version: 0.5.4
Summary: Authentication views for Keg
Home-page: https://github.com/level12/keg-login
Author: Level 12
Author-email: devteam@level12.io
License: UNKNOWN
Platform: UNKNOWN
Classifier: Development Status :: 4 - Beta
Classifier: Intended Audience :: Developers
Classifier: License :: OSI Approved :: BSD License
Classifier: Operating System :: OS Independent
Classifier: Programming Language :: Python :: 2.7
Classifier: Programming Language :: Python :: 3.4
Classifier: Programming Language :: Python :: 3.5
Requires-Dist: Flask-Login
Requires-Dist: Keg
Requires-Dist: KegElements
